<?xml version='1.0' encoding='UTF-8'?>
<root><OPHeading1>Business Today: Chamber</OPHeading1>
<DebateTimingRubric>9.30am Prayers</DebateTimingRubric>
<DebateTimingRubric>Followed by</DebateTimingRubric>
<OPHeading2>Questions</OPHeading2>
<QUESTIONS/>
<OPHeading2>Urgent Questions and Statements</OPHeading2>
<DebateTimingRubric>10.30am</DebateTimingRubric>
<DebateTimingRubric>Urgent Questions (if any)</DebateTimingRubric>
<DebateTimingRubric>Business Question to the Leader of the House</DebateTimingRubric>
<DebateTimingRubric>Ministerial Statements (if any)</DebateTimingRubric>
<OPHeading2>Presentation of Bills</OPHeading2>
<DebateTimingRubric>No debate<SOReference> (Standing Order No. 57)</SOReference></DebateTimingRubric>
<Heading3Underlined>Northern Ireland (Interim Arrangements) Bill</Heading3Underlined>
<MotionSponsor>Chris Heaton-Harris</MotionSponsor>
<MotionText><from_cdata>A Bill to extend the period during which departmental functions may be exercised in the absence of Ministers to cover the whole of the current period in which there is no Executive; to give the Secretary of State power, during that period, to commission advice and information for the purpose of developing options for raising more public revenue in Northern Ireland or otherwise improving the sustainability of public finances in Northern Ireland; and to require certain accounts and related documents to be laid before the House of Commons in periods in which the Northern Ireland Assembly is not functioning.</from_cdata></MotionText>
<OPHeading2>Business of the Day</OPHeading2>
<BusinessItemHeadingNumbered>BACKBENCH BUSINESS</BusinessItemHeadingNumbered>
<DebateTimingRubric>Until 5.00pm<SOReference> (Standing Order No. 9(3))</SOReference></DebateTimingRubric>
<NumberedHeadingIndented>Progress on reforms to NHS dentistry</NumberedHeadingIndented>
<MotionSponsorIndented>Judith Cummins</MotionSponsorIndented>
<MotionSponsorIndented>Peter Aldous</MotionSponsorIndented>
<MotionTextIndented><from_cdata>That this House has considered progress on reforms to NHS dentistry.</from_cdata></MotionTextIndented>
<Line_Interstitial_Indented> </Line_Interstitial_Indented>
<NumberedHeadingIndented>Reducing plastic pollution in the oceans</NumberedHeadingIndented>
<MotionSponsorIndented>Selaine Saxby</MotionSponsorIndented>
<MotionTextIndented><from_cdata>That this House has considered the matter of reducing plastic pollution in the oceans.</from_cdata></MotionTextIndented>
<NoteHeading>Notes:</NoteHeading>
<NoteText><from_cdata><p>The subjects for these debates were determined by the Backbench Business Committee.</p></from_cdata></NoteText>
<OPHeading2>Adjournment Debate</OPHeading2>
<DebateTimingRubric>Until 5.30pm or for half an hour (whichever is later)<SOReference> (Standing Order No. 9(7))</SOReference></DebateTimingRubric>
<MotionText>Political and security situation in Georgia: <PresenterSponsor>Adam Holloway</PresenterSponsor></MotionText>
<OPHeading1>Business Today: Westminster Hall</OPHeading1>
<OPHeading2>Order of Business</OPHeading2>
<DebateTimingRubric>The sitting will last for up to three hours (Standing Order No. 10(1))</DebateTimingRubric>
<DebateTimingRubric>1.30pm</DebateTimingRubric>
<MotionText>That this House has considered the Third Report of the Justice Committee, IPP Sentences, HC 266, and the Government response, HC 933: <PresenterSponsor>Sir Robert Neill</PresenterSponsor></MotionText>
<NoteHeading>Notes:</NoteHeading>
<NoteText><from_cdata>The subject of this debate was determined by the Liaison Committee.</from_cdata></NoteText>
<OPHeading1>Written Statements</OPHeading1>
<OPHeading2>Statements to be Made Today</OPHeading2>
<MotionCrossHeading>The Chancellor of the Exchequer</MotionCrossHeading>
<MinisterialStatement>Tax administration and maintenance: Spring 2023</MinisterialStatement>
<MotionCrossHeading>Secretary of State for Health and Social Care</MotionCrossHeading>
<MinisterialStatement>Health Update</MinisterialStatement>
<MotionCrossHeading>Secretary of State for the Home Department</MotionCrossHeading>
<MinisterialStatement>Independent Review of the Police-led Management of Registered Sex Offenders</MinisterialStatement>
<MotionCrossHeading>Secretary of State for Northern Ireland</MotionCrossHeading>
<MinisterialStatement>NI Finances 2023-24</MinisterialStatement>
<MotionCrossHeading>Prime Minister</MotionCrossHeading>
<MinisterialStatement>UK COVID-19 Inquiry</MinisterialStatement>
<MotionCrossHeading>Secretary of State for Transport</MotionCrossHeading>
<MinisterialStatement>Transport Update</MinisterialStatement>
<NoteHeading>Notes:</NoteHeading>
<NoteText>Texts of Written Statements are available from the Vote Office and on the internet at https://questions-statements.parliament.uk/ .</NoteText></root>